webql/__init__.py
webql/async_api/__init__.py
webql/async_api/core.py
webql/async_api/popup.py
webql/async_api/response_proxy.py
webql/async_api/session.py
webql/async_api/web/__init__.py
webql/async_api/web/network_monitor.py
webql/async_api/web/playwright_driver.py
webql/async_api/web/web_driver.py
webql/common/__init__.py
webql/common/api_constants.py
webql/common/aria_constants.py
webql/common/driver_constants.py
webql/common/driver_settings.py
webql/common/errors.py
webql/common/js_snippets/__init__.py
webql/common/js_snippets/add_dom_change_listener.js
webql/common/js_snippets/get_last_dom_change.js
webql/common/js_snippets/modify_dom.js
webql/common/js_snippets/remove_dom_change_listener.js
webql/common/js_snippets/scroll_to_bottom.js
webql/common/js_snippets/scroll_to_top.js
webql/common/js_snippets/serialize_dom.js
webql/common/js_snippets/snippet_loader.py
webql/common/syntax/__init__.py
webql/common/syntax/character_utils.py
webql/common/syntax/lexer.py
webql/common/syntax/node.py
webql/common/syntax/parser.py
webql/common/syntax/source.py
webql/common/syntax/token.py
webql/common/syntax/token_kind.py
webql/common/utils.py
webql/sync_api/__init__.py
webql/sync_api/core.py
webql/sync_api/popup.py
webql/sync_api/response_proxy.py
webql/sync_api/session.py
webql/sync_api/web/__init__.py
webql/sync_api/web/playwright_driver.py
webql/sync_api/web/web_driver.py
webql-0.2.8.dist-info/LICENSE
webql-0.2.8.dist-info/METADATA
webql-0.2.8.dist-info/WHEEL
webql-0.2.8.dist-info/RECORD
