Metadata-Version: 2.1
Name: webql
Version: 0.2.8
Summary: Tiny Fish AgentQL Python Client
License: MIT
Requires-Python: >=3.8,<4.0
Classifier: License :: OSI Approved :: MIT License
Classifier: Programming Language :: Python :: 3
Classifier: Programming Language :: Python :: 3.8
Classifier: Programming Language :: Python :: 3.9
Classifier: Programming Language :: Python :: 3.10
Classifier: Programming Language :: Python :: 3.11
Classifier: Programming Language :: Python :: 3.12
Requires-Dist: aiofiles (>=23,<24)
Requires-Dist: httpx (>=0.26,<0.27)
Requires-Dist: playwright (>=1,<2)
Requires-Dist: pydantic (>=2,<3)
Requires-Dist: pytest-asyncio (>=0.23,<0.24)
Requires-Dist: requests (>=2,<3)
Requires-Dist: tf-playwright-stealth
